pythondata_cpu_cv32e40x/__init__.py
pythondata_cpu_cv32e40x/system_verilog/.dir-locals.el
pythondata_cpu_cv32e40x/system_verilog/.gitignore
pythondata_cpu_cv32e40x/system_verilog/CONTRIBUTING.md
pythondata_cpu_cv32e40x/system_verilog/LICENSE
pythondata_cpu_cv32e40x/system_verilog/README.md
pythondata_cpu_cv32e40x/system_verilog/cv32e40x_manifest.flist
pythondata_cpu_cv32e40x/system_verilog/.github/release.yml
pythondata_cpu_cv32e40x/system_verilog/.github/ISSUE_TEMPLATE/bug.md
pythondata_cpu_cv32e40x/system_verilog/.github/ISSUE_TEMPLATE/config.yml
pythondata_cpu_cv32e40x/system_verilog/.github/ISSUE_TEMPLATE/enhancement.md
pythondata_cpu_cv32e40x/system_verilog/.github/ISSUE_TEMPLATE/question.md
pythondata_cpu_cv32e40x/system_verilog/.github/ISSUE_TEMPLATE/task.md
pythondata_cpu_cv32e40x/system_verilog/bhv/cv32e40x_core_log.sv
pythondata_cpu_cv32e40x/system_verilog/bhv/cv32e40x_dbg_helper.sv
pythondata_cpu_cv32e40x/system_verilog/bhv/cv32e40x_rvfi.sv
pythondata_cpu_cv32e40x/system_verilog/bhv/cv32e40x_rvfi_data_obi.sv
pythondata_cpu_cv32e40x/system_verilog/bhv/cv32e40x_rvfi_instr_obi.sv
pythondata_cpu_cv32e40x/system_verilog/bhv/cv32e40x_sim_clock_gate.sv
pythondata_cpu_cv32e40x/system_verilog/bhv/cv32e40x_wrapper.sv
pythondata_cpu_cv32e40x/system_verilog/bhv/rvfi_sim_trace.sv
pythondata_cpu_cv32e40x/system_verilog/bhv/include/cv32e40x_rvfi_pkg.sv
pythondata_cpu_cv32e40x/system_verilog/bhv/include/cv32e40x_wrapper.vh
pythondata_cpu_cv32e40x/system_verilog/constraints/cv32e40x_core.sdc
pythondata_cpu_cv32e40x/system_verilog/docs/.gitkeep
pythondata_cpu_cv32e40x/system_verilog/docs/user_manual/.gitignore
pythondata_cpu_cv32e40x/system_verilog/docs/user_manual/Makefile
pythondata_cpu_cv32e40x/system_verilog/docs/user_manual/make.bat
pythondata_cpu_cv32e40x/system_verilog/docs/user_manual/requirements.txt
pythondata_cpu_cv32e40x/system_verilog/docs/user_manual/images/Back_to_Back_Memory_Transaction.png
pythondata_cpu_cv32e40x-0.6.0.post161.dist-info/LICENSE
pythondata_cpu_cv32e40x-0.6.0.post161.dist-info/METADATA
pythondata_cpu_cv32e40x-0.6.0.post161.dist-info/WHEEL
pythondata_cpu_cv32e40x-0.6.0.post161.dist-info/top_level.txt
pythondata_cpu_cv32e40x-0.6.0.post161.dist-info/RECORD
